rpcclient/__init__.py
rpcclient/__main__.py
rpcclient/_version.py
rpcclient/client_manager.py
rpcclient/event_notifier.py
rpcclient/exceptions.py
rpcclient/registry.py
rpcclient/transports.py
rpcclient/utils.py
rpcclient/clients/__init__.py
rpcclient/clients/darwin/__init__.py
rpcclient/clients/darwin/client.py
rpcclient/clients/darwin/common.py
rpcclient/clients/darwin/consts.py
rpcclient/clients/darwin/structs.py
rpcclient/clients/darwin/symbol.py
rpcclient/clients/darwin/objective_c/__init__.py
rpcclient/clients/darwin/objective_c/autorelease_pool.py
rpcclient/clients/darwin/objective_c/objc.py
rpcclient/clients/darwin/objective_c/objective_c_class.py
rpcclient/clients/darwin/objective_c/objective_c_symbol.py
rpcclient/clients/darwin/subsystems/__init__.py
rpcclient/clients/darwin/subsystems/biome.py
rpcclient/clients/darwin/subsystems/bluetooth.py
rpcclient/clients/darwin/subsystems/cfpreferences.py
rpcclient/clients/darwin/subsystems/core_graphics.py
rpcclient/clients/darwin/subsystems/crash_reports.py
rpcclient/clients/darwin/subsystems/darwin_lief.py
rpcclient/clients/darwin/subsystems/duet.py
rpcclient/clients/darwin/subsystems/fs.py
rpcclient/clients/darwin/subsystems/hid.py
rpcclient/clients/darwin/subsystems/ioregistry.py
rpcclient/clients/darwin/subsystems/keychain.py
rpcclient/clients/darwin/subsystems/location.py
rpcclient/clients/darwin/subsystems/media.py
rpcclient/clients/darwin/subsystems/network.py
rpcclient/clients/darwin/subsystems/power.py
rpcclient/clients/darwin/subsystems/preferences.py
rpcclient/clients/darwin/subsystems/processes.py
rpcclient/clients/darwin/subsystems/reports.py
rpcclient/clients/darwin/subsystems/scpreferences.py
rpcclient/clients/darwin/subsystems/syslog.py
rpcclient/clients/darwin/subsystems/time.py
rpcclient/clients/darwin/subsystems/xpc.py
rpcclient/clients/ios/__init__.py
rpcclient/clients/ios/client.py
rpcclient/clients/ios/subsystems/__init__.py
rpcclient/clients/ios/subsystems/accessibility.py
rpcclient-6.10.0.dist-info/licenses/LICENSE
rpcclient-6.10.0.dist-info/METADATA
rpcclient-6.10.0.dist-info/WHEEL
rpcclient-6.10.0.dist-info/entry_points.txt
rpcclient-6.10.0.dist-info/top_level.txt
rpcclient-6.10.0.dist-info/RECORD
